MANIFEST.in
requirements.txt
setup.py
schrodinger/__init__.py
schrodinger/log.py
schrodinger/profile.py
schrodinger.egg-info/PKG-INFO
schrodinger.egg-info/SOURCES.txt
schrodinger.egg-info/dependency_links.txt
schrodinger.egg-info/requires.txt
schrodinger.egg-info/top_level.txt
schrodinger/tests/__init__.py
schrodinger/tests/test_logger.py
schrodinger/tests/test_profile.py