Metadata-Version: 1.0
Name: schrodinger
Version: 0.1
Summary: Tools to improve visibility into the running state of your code
Home-page: http://stormsherpa.com
Author: Shaun Kruger
Author-email: shaun.kruger@gmail.com
License: LGPL
Platform: UNKNOWN
